{
    "fixtures": [
        {
            "id": 130,
            "code": 2367667,
            "team_h": 18,
            "team_h_score": null,
            "team_a": 2,
            "team_a_score": null,
            "event": 13,
            "finished": false,
            "minutes": 0,
            "provisional_start_time": false,
            "kickoff_time": "2023-11-26T14:00:00Z",
            "event_name": "Gameweek 13",
            "is_home": false,
            "difficulty": 3
        },
        {
            "id": 132,
            "code": 2367668,
            "team_h": 3,
            "team_h_score": null,
            "team_a": 2,
            "team_a_score": null,
            "event": 14,
            "finished": false,
            "minutes": 0,
            "provisional_start_time": false,
            "kickoff_time": "2023-12-03T14:00:00Z",
            "event_name": "Gameweek 14",
            "is_home": false,
            "difficulty": 2
        },
        {
            "id": 141,
            "code": 2367678,
            "team_h": 2,
            "team_h_score": null,
            "team_a": 13,
            "team_a_score": null,
            "event": 15,
            "finished": false,
            "minutes": 0,
            "provisional_start_time": false,
            "kickoff_time": "2023-12-06T20:15:00Z",
            "event_name": "Gameweek 15",
            "is_home": true,
            "difficulty": 5
        },
        {
            "id": 151,
            "code": 2367688,
            "team_h": 2,
            "team_h_score": null,
            "team_a": 1,
            "team_a_score": null,
            "event": 16,
            "finished": false,
            "minutes": 0,
            "provisional_start_time": false,
            "kickoff_time": "2023-12-09T17:30:00Z",
            "event_name": "Gameweek 16",
            "is_home": true,
            "difficulty": 4
        },
        {
            "id": 163,
            "code": 2367700,
            "team_h": 4,
            "team_h_score": null,
            "team_a": 2,
            "team_a_score": null,
            "event": 17,
            "finished": false,
            "minutes": 0,
            "provisional_start_time": false,
            "kickoff_time": "2023-12-17T14:00:00Z",
            "event_name": "Gameweek 17",
            "is_home": false,
            "difficulty": 3
        },
        {
            "id": 171,
            "code": 2367708,
            "team_h": 2,
            "team_h_score": null,
            "team_a": 17,
            "team_a_score": null,
            "event": 18,
            "finished": false,
            "minutes": 0,
            "provisional_start_time": false,
            "kickoff_time": "2023-12-22T20:00:00Z",
            "event_name": "Gameweek 18",
            "is_home": true,
            "difficulty": 2
        },
        {
            "id": 188,
            "code": 2367725,
            "team_h": 14,
            "team_h_score": null,
            "team_a": 2,
            "team_a_score": null,
            "event": 19,
            "finished": false,
            "minutes": 0,
            "provisional_start_time": false,
            "kickoff_time": "2023-12-26T20:00:00Z",
            "event_name": "Gameweek 19",
            "is_home": false,
            "difficulty": 4
        },
        {
            "id": 191,
            "code": 2367728,
            "team_h": 2,
            "team_h_score": null,
            "team_a": 6,
            "team_a_score": null,
            "event": 20,
            "finished": false,
            "minutes": 0,
            "provisional_start_time": false,
            "kickoff_time": "2023-12-30T15:00:00Z",
            "event_name": "Gameweek 20",
            "is_home": true,
            "difficulty": 2
        },
        {
            "id": 207,
            "code": 2367744,
            "team_h": 9,
            "team_h_score": null,
            "team_a": 2,
            "team_a_score": null,
            "event": 21,
            "finished": false,
            "minutes": 0,
            "provisional_start_time": false,
            "kickoff_time": "2024-01-14T14:00:00Z",
            "event_name": "Gameweek 21",
            "is_home": false,
            "difficulty": 2
        },
        {
            "id": 211,
            "code": 2367748,
            "team_h": 2,
            "team_h_score": null,
            "team_a": 15,
            "team_a_score": null,
            "event": 22,
            "finished": false,
            "minutes": 0,
            "provisional_start_time": false,
            "kickoff_time": "2024-01-30T19:45:00Z",
            "event_name": "Gameweek 22",
            "is_home": true,
            "difficulty": 4
        },
        {
            "id": 230,
            "code": 2367767,
            "team_h": 17,
            "team_h_score": null,
            "team_a": 2,
            "team_a_score": null,
            "event": 23,
            "finished": false,
            "minutes": 0,
            "provisional_start_time": false,
            "kickoff_time": "2024-02-03T15:00:00Z",
            "event_name": "Gameweek 23",
            "is_home": false,
            "difficulty": 2
        },
        {
            "id": 231,
            "code": 2367768,
            "team_h": 2,
            "team_h_score": null,
            "team_a": 14,
            "team_a_score": null,
            "event": 24,
            "finished": false,
            "minutes": 0,
            "provisional_start_time": false,
            "kickoff_time": "2024-02-10T15:00:00Z",
            "event_name": "Gameweek 24",
            "is_home": true,
            "difficulty": 3
        },
        {
            "id": 244,
            "code": 2367781,
            "team_h": 10,
            "team_h_score": null,
            "team_a": 2,
            "team_a_score": null,
            "event": 25,
            "finished": false,
            "minutes": 0,
            "provisional_start_time": false,
            "kickoff_time": "2024-02-17T15:00:00Z",
            "event_name": "Gameweek 25",
            "is_home": false,
            "difficulty": 2
        },
        {
            "id": 252,
            "code": 2367790,
            "team_h": 2,
            "team_h_score": null,
            "team_a": 16,
            "team_a_score": null,
            "event": 26,
            "finished": false,
            "minutes": 0,
            "provisional_start_time": false,
            "kickoff_time": "2024-02-24T15:00:00Z",
            "event_name": "Gameweek 26",
            "is_home": true,
            "difficulty": 2
        },
        {
            "id": 265,
            "code": 2367802,
            "team_h": 12,
            "team_h_score": null,
            "team_a": 2,
            "team_a_score": null,
            "event": 27,
            "finished": false,
            "minutes": 0,
            "provisional_start_time": false,
            "kickoff_time": "2024-03-02T15:00:00Z",
            "event_name": "Gameweek 27",
            "is_home": false,
            "difficulty": 2
        },
        {
            "id": 272,
            "code": 2367810,
            "team_h": 2,
            "team_h_score": null,
            "team_a": 18,
            "team_a_score": null,
            "event": 28,
            "finished": false,
            "minutes": 0,
            "provisional_start_time": false,
            "kickoff_time": "2024-03-09T15:00:00Z",
            "event_name": "Gameweek 28",
            "is_home": true,
            "difficulty": 3
        },
        {
            "id": 289,
            "code": 2367826,
            "team_h": 19,
            "team_h_score": null,
            "team_a": 2,
            "team_a_score": null,
            "event": 29,
            "finished": false,
            "minutes": 0,
            "provisional_start_time": false,
            "kickoff_time": "2024-03-16T15:00:00Z",
            "event_name": "Gameweek 29",
            "is_home": false,
            "difficulty": 3
        },
        {
            "id": 291,
            "code": 2367829,
            "team_h": 2,
            "team_h_score": null,
            "team_a": 20,
            "team_a_score": null,
            "event": 30,
            "finished": false,
            "minutes": 0,
            "provisional_start_time": false,
            "kickoff_time": "2024-03-30T15:00:00Z",
            "event_name": "Gameweek 30",
            "is_home": true,
            "difficulty": 2
        },
        {
            "id": 309,
            "code": 2367846,
            "team_h": 13,
            "team_h_score": null,
            "team_a": 2,
            "team_a_score": null,
            "event": 31,
            "finished": false,
            "minutes": 0,
            "provisional_start_time": false,
            "kickoff_time": "2024-04-03T19:00:00Z",
            "event_name": "Gameweek 31",
            "is_home": false,
            "difficulty": 5
        },
        {
            "id": 311,
            "code": 2367848,
            "team_h": 2,
            "team_h_score": null,
            "team_a": 4,
            "team_a_score": null,
            "event": 32,
            "finished": false,
            "minutes": 0,
            "provisional_start_time": false,
            "kickoff_time": "2024-04-06T14:00:00Z",
            "event_name": "Gameweek 32",
            "is_home": true,
            "difficulty": 3
        },
        {
            "id": 321,
            "code": 2367859,
            "team_h": 1,
            "team_h_score": null,
            "team_a": 2,
            "team_a_score": null,
            "event": 33,
            "finished": false,
            "minutes": 0,
            "provisional_start_time": false,
            "kickoff_time": "2024-04-13T14:00:00Z",
            "event_name": "Gameweek 33",
            "is_home": false,
            "difficulty": 4
        },
        {
            "id": 331,
            "code": 2367868,
            "team_h": 2,
            "team_h_score": null,
            "team_a": 3,
            "team_a_score": null,
            "event": 34,
            "finished": false,
            "minutes": 0,
            "provisional_start_time": false,
            "kickoff_time": "2024-04-20T14:00:00Z",
            "event_name": "Gameweek 34",
            "is_home": true,
            "difficulty": 2
        },
        {
            "id": 341,
            "code": 2367879,
            "team_h": 2,
            "team_h_score": null,
            "team_a": 7,
            "team_a_score": null,
            "event": 35,
            "finished": false,
            "minutes": 0,
            "provisional_start_time": false,
            "kickoff_time": "2024-04-27T14:00:00Z",
            "event_name": "Gameweek 35",
            "is_home": true,
            "difficulty": 3
        },
        {
            "id": 353,
            "code": 2367890,
            "team_h": 5,
            "team_h_score": null,
            "team_a": 2,
            "team_a_score": null,
            "event": 36,
            "finished": false,
            "minutes": 0,
            "provisional_start_time": false,
            "kickoff_time": "2024-05-04T14:00:00Z",
            "event_name": "Gameweek 36",
            "is_home": false,
            "difficulty": 3
        },
        {
            "id": 361,
            "code": 2367899,
            "team_h": 2,
            "team_h_score": null,
            "team_a": 11,
            "team_a_score": null,
            "event": 37,
            "finished": false,
            "minutes": 0,
            "provisional_start_time": false,
            "kickoff_time": "2024-05-11T14:00:00Z",
            "event_name": "Gameweek 37",
            "is_home": true,
            "difficulty": 4
        },
        {
            "id": 376,
            "code": 2367913,
            "team_h": 8,
            "team_h_score": null,
            "team_a": 2,
            "team_a_score": null,
            "event": 38,
            "finished": false,
            "minutes": 0,
            "provisional_start_time": false,
            "kickoff_time": "2024-05-19T15:00:00Z",
            "event_name": "Gameweek 38",
            "is_home": false,
            "difficulty": 2
        }
    ],
    "history": [
        {
            "element": 44,
            "fixture": 6,
            "opponent_team": 15,
            "total_points": 0,
            "was_home": false,
            "kickoff_time": "2023-08-12T16:30:00Z",
            "team_h_score": 5,
            "team_a_score": 1,
            "round": 1,
            "minutes": 0,
            "goals_scored": 0,
            "assists": 0,
            "clean_sheets": 0,
            "goals_conceded": 0,
            "own_goals": 0,
            "penalties_saved": 0,
            "penalties_missed": 0,
            "yellow_cards": 0,
            "red_cards": 0,
            "saves": 0,
            "bonus": 0,
            "bps": 0,
            "influence": "0.0",
            "creativity": "0.0",
            "threat": "0.0",
            "ict_index": "0.0",
            "starts": 0,
            "expected_goals": "0.00",
            "expected_assists": "0.00",
            "expected_goal_involvements": "0.00",
            "expected_goals_conceded": "0.00",
            "value": 50,
            "transfers_balance": 0,
            "selected": 4236,
            "transfers_in": 0,
            "transfers_out": 0
        },
        {
            "element": 44,
            "fixture": 11,
            "opponent_team": 9,
            "total_points": 7,
            "was_home": true,
            "kickoff_time": "2023-08-20T13:00:00Z",
            "team_h_score": 4,
            "team_a_score": 0,
            "round": 2,
            "minutes": 16,
            "goals_scored": 1,
            "assists": 0,
            "clean_sheets": 0,
            "goals_conceded": 0,
            "own_goals": 0,
            "penalties_saved": 0,
            "penalties_missed": 0,
            "yellow_cards": 0,
            "red_cards": 0,
            "saves": 0,
            "bonus": 2,
            "bps": 31,
            "influence": "38.2",
            "creativity": "11.7",
            "threat": "19.0",
            "ict_index": "6.9",
            "starts": 0,
            "expected_goals": "0.55",
            "expected_assists": "0.00",
            "expected_goal_involvements": "0.55",
            "expected_goals_conceded": "0.03",
            "value": 50,
            "transfers_balance": -1228,
            "selected": 3101,
            "transfers_in": 67,
            "transfers_out": 1295
        },
        {
            "element": 44,
            "fixture": 25,
            "opponent_team": 6,
            "total_points": 1,
            "was_home": false,
            "kickoff_time": "2023-08-27T13:00:00Z",
            "team_h_score": 1,
            "team_a_score": 3,
            "round": 3,
            "minutes": 4,
            "goals_scored": 0,
            "assists": 0,
            "clean_sheets": 0,
            "goals_conceded": 0,
            "own_goals": 0,
            "penalties_saved": 0,
            "penalties_missed": 0,
            "yellow_cards": 0,
            "red_cards": 0,
            "saves": 0,
            "bonus": 0,
            "bps": 3,
            "influence": "0.0",
            "creativity": "0.0",
            "threat": "2.0",
            "ict_index": "0.2",
            "starts": 0,
            "expected_goals": "0.00",
            "expected_assists": "0.00",
            "expected_goal_involvements": "0.00",
            "expected_goals_conceded": "0.33",
            "value": 50,
            "transfers_balance": 5987,
            "selected": 11960,
            "transfers_in": 7315,
            "transfers_out": 1328
        },
        {
            "element": 44,
            "fixture": 37,
            "opponent_team": 11,
            "total_points": 1,
            "was_home": false,
            "kickoff_time": "2023-09-03T13:00:00Z",
            "team_h_score": 3,
            "team_a_score": 0,
            "round": 4,
            "minutes": 17,
            "goals_scored": 0,
            "assists": 0,
            "clean_sheets": 0,
            "goals_conceded": 0,
            "own_goals": 0,
            "penalties_saved": 0,
            "penalties_missed": 0,
            "yellow_cards": 0,
            "red_cards": 0,
            "saves": 0,
            "bonus": 0,
            "bps": -1,
            "influence": "0.0",
            "creativity": "0.8",
            "threat": "8.0",
            "ict_index": "0.4",
            "starts": 0,
            "expected_goals": "0.08",
            "expected_assists": "0.01",
            "expected_goal_involvements": "0.09",
            "expected_goals_conceded": "0.12",
            "value": 50,
            "transfers_balance": -311,
            "selected": 12358,
            "transfers_in": 2128,
            "transfers_out": 2439
        },
        {
            "element": 44,
            "fixture": 41,
            "opponent_team": 8,
            "total_points": 5,
            "was_home": true,
            "kickoff_time": "2023-09-16T14:00:00Z",
            "team_h_score": 3,
            "team_a_score": 1,
            "round": 5,
            "minutes": 19,
            "goals_scored": 1,
            "assists": 0,
            "clean_sheets": 0,
            "goals_conceded": 0,
            "own_goals": 0,
            "penalties_saved": 0,
            "penalties_missed": 0,
            "yellow_cards": 1,
            "red_cards": 0,
            "saves": 0,
            "bonus": 1,
            "bps": 23,
            "influence": "34.2",
            "creativity": "0.4",
            "threat": "26.0",
            "ict_index": "6.1",
            "starts": 0,
            "expected_goals": "0.10",
            "expected_assists": "0.00",
            "expected_goal_involvements": "0.10",
            "expected_goals_conceded": "0.35",
            "value": 50,
            "transfers_balance": 553,
            "selected": 14493,
            "transfers_in": 2735,
            "transfers_out": 2182
        },
        {
            "element": 44,
            "fixture": 55,
            "opponent_team": 7,
            "total_points": 1,
            "was_home": false,
            "kickoff_time": "2023-09-24T13:00:00Z",
            "team_h_score": 0,
            "team_a_score": 1,
            "round": 6,
            "minutes": 1,
            "goals_scored": 0,
            "assists": 0,
            "clean_sheets": 0,
            "goals_conceded": 0,
            "own_goals": 0,
            "penalties_saved": 0,
            "penalties_missed": 0,
            "yellow_cards": 0,
            "red_cards": 0,
            "saves": 0,
            "bonus": 0,
            "bps": 0,
            "influence": "0.0",
            "creativity": "0.8",
            "threat": "0.0",
            "ict_index": "0.0",
            "starts": 0,
            "expected_goals": "0.00",
            "expected_assists": "0.00",
            "expected_goal_involvements": "0.00",
            "expected_goals_conceded": "0.19",
            "value": 50,
            "transfers_balance": 7068,
            "selected": 22756,
            "transfers_in": 9270,
            "transfers_out": 2202
        },
        {
            "element": 44,
            "fixture": 61,
            "opponent_team": 5,
            "total_points": 0,
            "was_home": true,
            "kickoff_time": "2023-09-30T11:30:00Z",
            "team_h_score": 6,
            "team_a_score": 1,
            "round": 7,
            "minutes": 11,
            "goals_scored": 0,
            "assists": 0,
            "clean_sheets": 0,
            "goals_conceded": 0,
            "own_goals": 0,
            "penalties_saved": 0,
            "penalties_missed": 0,
            "yellow_cards": 1,
            "red_cards": 0,
            "saves": 0,
            "bonus": 0,
            "bps": -1,
            "influence": "0.2",
            "creativity": "0.5",
            "threat": "0.0",
            "ict_index": "0.1",
            "starts": 0,
            "expected_goals": "0.00",
            "expected_assists": "0.00",
            "expected_goal_involvements": "0.00",
            "expected_goals_conceded": "0.10",
            "value": 50,
            "transfers_balance": 6620,
            "selected": 30560,
            "transfers_in": 10803,
            "transfers_out": 4183
        },
        {
            "element": 44,
            "fixture": 80,
            "opponent_team": 20,
            "total_points": 0,
            "was_home": false,
            "kickoff_time": "2023-10-08T13:00:00Z",
            "team_h_score": 1,
            "team_a_score": 1,
            "round": 8,
            "minutes": 0,
            "goals_scored": 0,
            "assists": 0,
            "clean_sheets": 0,
            "goals_conceded": 0,
            "own_goals": 0,
            "penalties_saved": 0,
            "penalties_missed": 0,
            "yellow_cards": 0,
            "red_cards": 0,
            "saves": 0,
            "bonus": 0,
            "bps": 0,
            "influence": "0.0",
            "creativity": "0.0",
            "threat": "0.0",
            "ict_index": "0.0",
            "starts": 0,
            "expected_goals": "0.00",
            "expected_assists": "0.00",
            "expected_goal_involvements": "0.00",
            "expected_goals_conceded": "0.00",
            "value": 50,
            "transfers_balance": -1529,
            "selected": 28888,
            "transfers_in": 4147,
            "transfers_out": 5676
        },
        {
            "element": 44,
            "fixture": 81,
            "opponent_team": 19,
            "total_points": 0,
            "was_home": true,
            "kickoff_time": "2023-10-22T15:30:00Z",
            "team_h_score": 4,
            "team_a_score": 1,
            "round": 9,
            "minutes": 0,
            "goals_scored": 0,
            "assists": 0,
            "clean_sheets": 0,
            "goals_conceded": 0,
            "own_goals": 0,
            "penalties_saved": 0,
            "penalties_missed": 0,
            "yellow_cards": 0,
            "red_cards": 0,
            "saves": 0,
            "bonus": 0,
            "bps": 0,
            "influence": "0.0",
            "creativity": "0.0",
            "threat": "0.0",
            "ict_index": "0.0",
            "starts": 0,
            "expected_goals": "0.00",
            "expected_assists": "0.00",
            "expected_goal_involvements": "0.00",
            "expected_goals_conceded": "0.00",
            "value": 50,
            "transfers_balance": -1562,
            "selected": 27939,
            "transfers_in": 2183,
            "transfers_out": 3745
        },
        {
            "element": 44,
            "fixture": 92,
            "opponent_team": 12,
            "total_points": 0,
            "was_home": true,
            "kickoff_time": "2023-10-29T14:00:00Z",
            "team_h_score": 3,
            "team_a_score": 1,
            "round": 10,
            "minutes": 0,
            "goals_scored": 0,
            "assists": 0,
            "clean_sheets": 0,
            "goals_conceded": 0,
            "own_goals": 0,
            "penalties_saved": 0,
            "penalties_missed": 0,
            "yellow_cards": 0,
            "red_cards": 0,
            "saves": 0,
            "bonus": 0,
            "bps": 0,
            "influence": "0.0",
            "creativity": "0.0",
            "threat": "0.0",
            "ict_index": "0.0",
            "starts": 0,
            "expected_goals": "0.00",
            "expected_assists": "0.00",
            "expected_goal_involvements": "0.00",
            "expected_goals_conceded": "0.00",
            "value": 50,
            "transfers_balance": -1760,
            "selected": 26484,
            "transfers_in": 2195,
            "transfers_out": 3955
        },
        {
            "element": 44,
            "fixture": 108,
            "opponent_team": 16,
            "total_points": 0,
            "was_home": false,
            "kickoff_time": "2023-11-05T14:00:00Z",
            "team_h_score": 2,
            "team_a_score": 0,
            "round": 11,
            "minutes": 0,
            "goals_scored": 0,
            "assists": 0,
            "clean_sheets": 0,
            "goals_conceded": 0,
            "own_goals": 0,
            "penalties_saved": 0,
            "penalties_missed": 0,
            "yellow_cards": 0,
            "red_cards": 0,
            "saves": 0,
            "bonus": 0,
            "bps": 0,
            "influence": "0.0",
            "creativity": "0.0",
            "threat": "0.0",
            "ict_index": "0.0",
            "starts": 0,
            "expected_goals": "0.00",
            "expected_assists": "0.00",
            "expected_goal_involvements": "0.00",
            "expected_goals_conceded": "0.00",
            "value": 50,
            "transfers_balance": -4107,
            "selected": 22445,
            "transfers_in": 777,
            "transfers_out": 4884
        },
        {
            "element": 44,
            "fixture": 112,
            "opponent_team": 10,
            "total_points": 0,
            "was_home": true,
            "kickoff_time": "2023-11-12T14:00:00Z",
            "team_h_score": 3,
            "team_a_score": 1,
            "round": 12,
            "minutes": 0,
            "goals_scored": 0,
            "assists": 0,
            "clean_sheets": 0,
            "goals_conceded": 0,
            "own_goals": 0,
            "penalties_saved": 0,
            "penalties_missed": 0,
            "yellow_cards": 0,
            "red_cards": 0,
            "saves": 0,
            "bonus": 0,
            "bps": 0,
            "influence": "0.0",
            "creativity": "0.0",
            "threat": "0.0",
            "ict_index": "0.0",
            "starts": 0,
            "expected_goals": "0.00",
            "expected_assists": "0.00",
            "expected_goal_involvements": "0.00",
            "expected_goals_conceded": "0.00",
            "value": 50,
            "transfers_balance": -1679,
            "selected": 20990,
            "transfers_in": 778,
            "transfers_out": 2457
        }
    ],
    "history_past": [
        {
            "season_name": "2022/23",
            "element_code": 476344,
            "start_cost": 55,
            "end_cost": 55,
            "total_points": 11,
            "minutes": 126,
            "goals_scored": 0,
            "assists": 0,
            "clean_sheets": 0,
            "goals_conceded": 4,
            "own_goals": 0,
            "penalties_saved": 0,
            "penalties_missed": 0,
            "yellow_cards": 1,
            "red_cards": 0,
            "saves": 0,
            "bonus": 0,
            "bps": 15,
            "influence": "12.8",
            "creativity": "13.4",
            "threat": "51.0",
            "ict_index": "7.4",
            "starts": 0,
            "expected_goals": "0.59",
            "expected_assists": "0.02",
            "expected_goal_involvements": "0.61",
            "expected_goals_conceded": "3.88"
        }
    ]
}