{
    "fixtures": [
        {
            "id": 126,
            "code": 2367663,
            "team_h": 13,
            "team_h_score": null,
            "team_a": 11,
            "team_a_score": null,
            "event": 13,
            "finished": false,
            "minutes": 0,
            "provisional_start_time": false,
            "kickoff_time": "2023-11-25T12:30:00Z",
            "event_name": "Gameweek 13",
            "is_home": false,
            "difficulty": 5
        },
        {
            "id": 136,
            "code": 2367673,
            "team_h": 11,
            "team_h_score": null,
            "team_a": 10,
            "team_a_score": null,
            "event": 14,
            "finished": false,
            "minutes": 0,
            "provisional_start_time": false,
            "kickoff_time": "2023-12-03T14:00:00Z",
            "event_name": "Gameweek 14",
            "is_home": true,
            "difficulty": 2
        },
        {
            "id": 147,
            "code": 2367684,
            "team_h": 17,
            "team_h_score": null,
            "team_a": 11,
            "team_a_score": null,
            "event": 15,
            "finished": false,
            "minutes": 0,
            "provisional_start_time": false,
            "kickoff_time": "2023-12-06T19:30:00Z",
            "event_name": "Gameweek 15",
            "is_home": false,
            "difficulty": 2
        },
        {
            "id": 153,
            "code": 2367690,
            "team_h": 8,
            "team_h_score": null,
            "team_a": 11,
            "team_a_score": null,
            "event": 16,
            "finished": false,
            "minutes": 0,
            "provisional_start_time": false,
            "kickoff_time": "2023-12-09T12:30:00Z",
            "event_name": "Gameweek 16",
            "is_home": false,
            "difficulty": 2
        },
        {
            "id": 166,
            "code": 2367703,
            "team_h": 11,
            "team_h_score": null,
            "team_a": 14,
            "team_a_score": null,
            "event": 17,
            "finished": false,
            "minutes": 0,
            "provisional_start_time": false,
            "kickoff_time": "2023-12-17T16:30:00Z",
            "event_name": "Gameweek 17",
            "is_home": true,
            "difficulty": 3
        },
        {
            "id": 174,
            "code": 2367711,
            "team_h": 11,
            "team_h_score": null,
            "team_a": 1,
            "team_a_score": null,
            "event": 18,
            "finished": false,
            "minutes": 0,
            "provisional_start_time": false,
            "kickoff_time": "2023-12-23T17:30:00Z",
            "event_name": "Gameweek 18",
            "is_home": true,
            "difficulty": 4
        },
        {
            "id": 185,
            "code": 2367722,
            "team_h": 6,
            "team_h_score": null,
            "team_a": 11,
            "team_a_score": null,
            "event": 19,
            "finished": false,
            "minutes": 0,
            "provisional_start_time": false,
            "kickoff_time": "2023-12-26T17:30:00Z",
            "event_name": "Gameweek 19",
            "is_home": false,
            "difficulty": 2
        },
        {
            "id": 194,
            "code": 2367731,
            "team_h": 11,
            "team_h_score": null,
            "team_a": 15,
            "team_a_score": null,
            "event": 20,
            "finished": false,
            "minutes": 0,
            "provisional_start_time": false,
            "kickoff_time": "2024-01-01T20:00:00Z",
            "event_name": "Gameweek 20",
            "is_home": true,
            "difficulty": 4
        },
        {
            "id": 202,
            "code": 2367738,
            "team_h": 3,
            "team_h_score": null,
            "team_a": 11,
            "team_a_score": null,
            "event": 21,
            "finished": false,
            "minutes": 0,
            "provisional_start_time": false,
            "kickoff_time": "2024-01-21T16:30:00Z",
            "event_name": "Gameweek 21",
            "is_home": false,
            "difficulty": 2
        },
        {
            "id": 219,
            "code": 2367756,
            "team_h": 11,
            "team_h_score": null,
            "team_a": 7,
            "team_a_score": null,
            "event": 22,
            "finished": false,
            "minutes": 0,
            "provisional_start_time": false,
            "kickoff_time": "2024-01-31T20:00:00Z",
            "event_name": "Gameweek 22",
            "is_home": true,
            "difficulty": 3
        },
        {
            "id": 221,
            "code": 2367759,
            "team_h": 1,
            "team_h_score": null,
            "team_a": 11,
            "team_a_score": null,
            "event": 23,
            "finished": false,
            "minutes": 0,
            "provisional_start_time": false,
            "kickoff_time": "2024-02-03T15:00:00Z",
            "event_name": "Gameweek 23",
            "is_home": false,
            "difficulty": 4
        },
        {
            "id": 234,
            "code": 2367771,
            "team_h": 11,
            "team_h_score": null,
            "team_a": 6,
            "team_a_score": null,
            "event": 24,
            "finished": false,
            "minutes": 0,
            "provisional_start_time": false,
            "kickoff_time": "2024-02-10T15:00:00Z",
            "event_name": "Gameweek 24",
            "is_home": true,
            "difficulty": 2
        },
        {
            "id": 241,
            "code": 2367778,
            "team_h": 4,
            "team_h_score": null,
            "team_a": 11,
            "team_a_score": null,
            "event": 25,
            "finished": false,
            "minutes": 0,
            "provisional_start_time": false,
            "kickoff_time": "2024-02-17T15:00:00Z",
            "event_name": "Gameweek 25",
            "is_home": false,
            "difficulty": 3
        },
        {
            "id": 257,
            "code": 2367794,
            "team_h": 11,
            "team_h_score": null,
            "team_a": 12,
            "team_a_score": null,
            "event": 26,
            "finished": false,
            "minutes": 0,
            "provisional_start_time": false,
            "kickoff_time": "2024-02-24T15:00:00Z",
            "event_name": "Gameweek 26",
            "is_home": true,
            "difficulty": 2
        },
        {
            "id": 268,
            "code": 2367805,
            "team_h": 16,
            "team_h_score": null,
            "team_a": 11,
            "team_a_score": null,
            "event": 27,
            "finished": false,
            "minutes": 0,
            "provisional_start_time": false,
            "kickoff_time": "2024-03-02T15:00:00Z",
            "event_name": "Gameweek 27",
            "is_home": false,
            "difficulty": 2
        },
        {
            "id": 277,
            "code": 2367814,
            "team_h": 11,
            "team_h_score": null,
            "team_a": 13,
            "team_a_score": null,
            "event": 28,
            "finished": false,
            "minutes": 0,
            "provisional_start_time": false,
            "kickoff_time": "2024-03-09T15:00:00Z",
            "event_name": "Gameweek 28",
            "is_home": true,
            "difficulty": 5
        },
        {
            "id": 285,
            "code": 2367822,
            "team_h": 9,
            "team_h_score": null,
            "team_a": 11,
            "team_a_score": null,
            "event": 29,
            "finished": false,
            "minutes": 0,
            "provisional_start_time": false,
            "kickoff_time": "2024-03-16T15:00:00Z",
            "event_name": "Gameweek 29",
            "is_home": false,
            "difficulty": 2
        },
        {
            "id": 295,
            "code": 2367832,
            "team_h": 11,
            "team_h_score": null,
            "team_a": 5,
            "team_a_score": null,
            "event": 30,
            "finished": false,
            "minutes": 0,
            "provisional_start_time": false,
            "kickoff_time": "2024-03-30T15:00:00Z",
            "event_name": "Gameweek 30",
            "is_home": true,
            "difficulty": 3
        },
        {
            "id": 308,
            "code": 2367845,
            "team_h": 11,
            "team_h_score": null,
            "team_a": 17,
            "team_a_score": null,
            "event": 31,
            "finished": false,
            "minutes": 0,
            "provisional_start_time": false,
            "kickoff_time": "2024-04-03T19:00:00Z",
            "event_name": "Gameweek 31",
            "is_home": true,
            "difficulty": 2
        },
        {
            "id": 317,
            "code": 2367854,
            "team_h": 14,
            "team_h_score": null,
            "team_a": 11,
            "team_a_score": null,
            "event": 32,
            "finished": false,
            "minutes": 0,
            "provisional_start_time": false,
            "kickoff_time": "2024-04-06T14:00:00Z",
            "event_name": "Gameweek 32",
            "is_home": false,
            "difficulty": 4
        },
        {
            "id": 326,
            "code": 2367863,
            "team_h": 11,
            "team_h_score": null,
            "team_a": 8,
            "team_a_score": null,
            "event": 33,
            "finished": false,
            "minutes": 0,
            "provisional_start_time": false,
            "kickoff_time": "2024-04-13T14:00:00Z",
            "event_name": "Gameweek 33",
            "is_home": true,
            "difficulty": 2
        },
        {
            "id": 335,
            "code": 2367872,
            "team_h": 10,
            "team_h_score": null,
            "team_a": 11,
            "team_a_score": null,
            "event": 34,
            "finished": false,
            "minutes": 0,
            "provisional_start_time": false,
            "kickoff_time": "2024-04-20T14:00:00Z",
            "event_name": "Gameweek 34",
            "is_home": false,
            "difficulty": 2
        },
        {
            "id": 349,
            "code": 2367886,
            "team_h": 19,
            "team_h_score": null,
            "team_a": 11,
            "team_a_score": null,
            "event": 35,
            "finished": false,
            "minutes": 0,
            "provisional_start_time": false,
            "kickoff_time": "2024-04-27T14:00:00Z",
            "event_name": "Gameweek 35",
            "is_home": false,
            "difficulty": 3
        },
        {
            "id": 357,
            "code": 2367894,
            "team_h": 11,
            "team_h_score": null,
            "team_a": 18,
            "team_a_score": null,
            "event": 36,
            "finished": false,
            "minutes": 0,
            "provisional_start_time": false,
            "kickoff_time": "2024-05-04T14:00:00Z",
            "event_name": "Gameweek 36",
            "is_home": true,
            "difficulty": 3
        },
        {
            "id": 361,
            "code": 2367899,
            "team_h": 2,
            "team_h_score": null,
            "team_a": 11,
            "team_a_score": null,
            "event": 37,
            "finished": false,
            "minutes": 0,
            "provisional_start_time": false,
            "kickoff_time": "2024-05-11T14:00:00Z",
            "event_name": "Gameweek 37",
            "is_home": false,
            "difficulty": 3
        },
        {
            "id": 377,
            "code": 2367914,
            "team_h": 11,
            "team_h_score": null,
            "team_a": 20,
            "team_a_score": null,
            "event": 38,
            "finished": false,
            "minutes": 0,
            "provisional_start_time": false,
            "kickoff_time": "2024-05-19T15:00:00Z",
            "event_name": "Gameweek 38",
            "is_home": true,
            "difficulty": 2
        }
    ],
    "history": [
        {
            "element": 297,
            "fixture": 9,
            "opponent_team": 7,
            "total_points": 2,
            "was_home": false,
            "kickoff_time": "2023-08-13T15:30:00Z",
            "team_h_score": 1,
            "team_a_score": 1,
            "round": 1,
            "minutes": 65,
            "goals_scored": 0,
            "assists": 0,
            "clean_sheets": 0,
            "goals_conceded": 1,
            "own_goals": 0,
            "penalties_saved": 0,
            "penalties_missed": 0,
            "yellow_cards": 0,
            "red_cards": 0,
            "saves": 0,
            "bonus": 0,
            "bps": 5,
            "influence": "8.0",
            "creativity": "10.9",
            "threat": "2.0",
            "ict_index": "2.1",
            "starts": 1,
            "expected_goals": "0.00",
            "expected_assists": "0.05",
            "expected_goal_involvements": "0.05",
            "expected_goals_conceded": "1.04",
            "value": 75,
            "transfers_balance": 0,
            "selected": 527528,
            "transfers_in": 0,
            "transfers_out": 0
        },
        {
            "element": 297,
            "fixture": 14,
            "opponent_team": 3,
            "total_points": 2,
            "was_home": true,
            "kickoff_time": "2023-08-19T14:00:00Z",
            "team_h_score": 3,
            "team_a_score": 1,
            "round": 2,
            "minutes": 62,
            "goals_scored": 0,
            "assists": 0,
            "clean_sheets": 0,
            "goals_conceded": 1,
            "own_goals": 0,
            "penalties_saved": 0,
            "penalties_missed": 0,
            "yellow_cards": 0,
            "red_cards": 0,
            "saves": 0,
            "bonus": 0,
            "bps": 10,
            "influence": "5.6",
            "creativity": "11.8",
            "threat": "11.0",
            "ict_index": "2.8",
            "starts": 1,
            "expected_goals": "0.24",
            "expected_assists": "0.04",
            "expected_goal_involvements": "0.28",
            "expected_goals_conceded": "0.19",
            "value": 75,
            "transfers_balance": -31755,
            "selected": 570407,
            "transfers_in": 47557,
            "transfers_out": 79312
        },
        {
            "element": 297,
            "fixture": 29,
            "opponent_team": 15,
            "total_points": 1,
            "was_home": false,
            "kickoff_time": "2023-08-27T15:30:00Z",
            "team_h_score": 1,
            "team_a_score": 2,
            "round": 3,
            "minutes": 57,
            "goals_scored": 0,
            "assists": 0,
            "clean_sheets": 0,
            "goals_conceded": 1,
            "own_goals": 0,
            "penalties_saved": 0,
            "penalties_missed": 0,
            "yellow_cards": 0,
            "red_cards": 0,
            "saves": 0,
            "bonus": 0,
            "bps": 2,
            "influence": "4.6",
            "creativity": "10.6",
            "threat": "4.0",
            "ict_index": "1.9",
            "starts": 1,
            "expected_goals": "0.00",
            "expected_assists": "0.00",
            "expected_goal_involvements": "0.00",
            "expected_goals_conceded": "1.25",
            "value": 74,
            "transfers_balance": -125154,
            "selected": 462761,
            "transfers_in": 19028,
            "transfers_out": 144182
        },
        {
            "element": 297,
            "fixture": 37,
            "opponent_team": 2,
            "total_points": 1,
            "was_home": true,
            "kickoff_time": "2023-09-03T13:00:00Z",
            "team_h_score": 3,
            "team_a_score": 0,
            "round": 4,
            "minutes": 25,
            "goals_scored": 0,
            "assists": 0,
            "clean_sheets": 0,
            "goals_conceded": 0,
            "own_goals": 0,
            "penalties_saved": 0,
            "penalties_missed": 0,
            "yellow_cards": 0,
            "red_cards": 0,
            "saves": 0,
            "bonus": 0,
            "bps": 1,
            "influence": "0.0",
            "creativity": "0.3",
            "threat": "4.0",
            "ict_index": "0.3",
            "starts": 0,
            "expected_goals": "0.00",
            "expected_assists": "0.01",
            "expected_goal_involvements": "0.01",
            "expected_goals_conceded": "0.08",
            "value": 74,
            "transfers_balance": -80836,
            "selected": 391910,
            "transfers_in": 7654,
            "transfers_out": 88490
        },
        {
            "element": 297,
            "fixture": 50,
            "opponent_team": 20,
            "total_points": 6,
            "was_home": false,
            "kickoff_time": "2023-09-16T11:30:00Z",
            "team_h_score": 1,
            "team_a_score": 3,
            "round": 5,
            "minutes": 55,
            "goals_scored": 1,
            "assists": 0,
            "clean_sheets": 0,
            "goals_conceded": 1,
            "own_goals": 0,
            "penalties_saved": 0,
            "penalties_missed": 0,
            "yellow_cards": 0,
            "red_cards": 0,
            "saves": 0,
            "bonus": 1,
            "bps": 24,
            "influence": "31.6",
            "creativity": "1.7",
            "threat": "45.0",
            "ict_index": "7.8",
            "starts": 1,
            "expected_goals": "1.08",
            "expected_assists": "0.01",
            "expected_goal_involvements": "1.09",
            "expected_goals_conceded": "0.40",
            "value": 73,
            "transfers_balance": -71400,
            "selected": 329301,
            "transfers_in": 10227,
            "transfers_out": 81627
        },
        {
            "element": 297,
            "fixture": 57,
            "opponent_team": 19,
            "total_points": 1,
            "was_home": true,
            "kickoff_time": "2023-09-24T13:00:00Z",
            "team_h_score": 3,
            "team_a_score": 1,
            "round": 6,
            "minutes": 9,
            "goals_scored": 0,
            "assists": 0,
            "clean_sheets": 0,
            "goals_conceded": 0,
            "own_goals": 0,
            "penalties_saved": 0,
            "penalties_missed": 0,
            "yellow_cards": 0,
            "red_cards": 0,
            "saves": 0,
            "bonus": 0,
            "bps": -1,
            "influence": "3.4",
            "creativity": "0.6",
            "threat": "26.0",
            "ict_index": "3.0",
            "starts": 0,
            "expected_goals": "0.24",
            "expected_assists": "0.00",
            "expected_goal_involvements": "0.24",
            "expected_goals_conceded": "0.02",
            "value": 73,
            "transfers_balance": -7622,
            "selected": 327609,
            "transfers_in": 16356,
            "transfers_out": 23978
        },
        {
            "element": 297,
            "fixture": 68,
            "opponent_team": 18,
            "total_points": 7,
            "was_home": false,
            "kickoff_time": "2023-09-30T16:30:00Z",
            "team_h_score": 2,
            "team_a_score": 1,
            "round": 7,
            "minutes": 45,
            "goals_scored": 1,
            "assists": 0,
            "clean_sheets": 0,
            "goals_conceded": 1,
            "own_goals": 0,
            "penalties_saved": 0,
            "penalties_missed": 0,
            "yellow_cards": 0,
            "red_cards": 0,
            "saves": 0,
            "bonus": 2,
            "bps": 27,
            "influence": "37.4",
            "creativity": "11.3",
            "threat": "39.0",
            "ict_index": "8.8",
            "starts": 1,
            "expected_goals": "0.43",
            "expected_assists": "0.05",
            "expected_goal_involvements": "0.48",
            "expected_goals_conceded": "1.07",
            "value": 72,
            "transfers_balance": -29005,
            "selected": 300360,
            "transfers_in": 8555,
            "transfers_out": 37560
        },
        {
            "element": 297,
            "fixture": 72,
            "opponent_team": 5,
            "total_points": 0,
            "was_home": false,
            "kickoff_time": "2023-10-08T13:00:00Z",
            "team_h_score": 2,
            "team_a_score": 2,
            "round": 8,
            "minutes": 0,
            "goals_scored": 0,
            "assists": 0,
            "clean_sheets": 0,
            "goals_conceded": 0,
            "own_goals": 0,
            "penalties_saved": 0,
            "penalties_missed": 0,
            "yellow_cards": 0,
            "red_cards": 0,
            "saves": 0,
            "bonus": 0,
            "bps": 0,
            "influence": "0.0",
            "creativity": "0.0",
            "threat": "0.0",
            "ict_index": "0.0",
            "starts": 0,
            "expected_goals": "0.00",
            "expected_assists": "0.00",
            "expected_goal_involvements": "0.00",
            "expected_goals_conceded": "0.00",
            "value": 72,
            "transfers_balance": -38650,
            "selected": 262732,
            "transfers_in": 5997,
            "transfers_out": 44647
        },
        {
            "element": 297,
            "fixture": 85,
            "opponent_team": 9,
            "total_points": 0,
            "was_home": true,
            "kickoff_time": "2023-10-21T11:30:00Z",
            "team_h_score": 2,
            "team_a_score": 0,
            "round": 9,
            "minutes": 0,
            "goals_scored": 0,
            "assists": 0,
            "clean_sheets": 0,
            "goals_conceded": 0,
            "own_goals": 0,
            "penalties_saved": 0,
            "penalties_missed": 0,
            "yellow_cards": 0,
            "red_cards": 0,
            "saves": 0,
            "bonus": 0,
            "bps": 0,
            "influence": "0.0",
            "creativity": "0.0",
            "threat": "0.0",
            "ict_index": "0.0",
            "starts": 0,
            "expected_goals": "0.00",
            "expected_assists": "0.00",
            "expected_goal_involvements": "0.00",
            "expected_goals_conceded": "0.00",
            "value": 72,
            "transfers_balance": -29427,
            "selected": 234620,
            "transfers_in": 1523,
            "transfers_out": 30950
        },
        {
            "element": 297,
            "fixture": 97,
            "opponent_team": 16,
            "total_points": 1,
            "was_home": true,
            "kickoff_time": "2023-10-29T14:00:00Z",
            "team_h_score": 3,
            "team_a_score": 0,
            "round": 10,
            "minutes": 32,
            "goals_scored": 0,
            "assists": 0,
            "clean_sheets": 0,
            "goals_conceded": 0,
            "own_goals": 0,
            "penalties_saved": 0,
            "penalties_missed": 0,
            "yellow_cards": 0,
            "red_cards": 0,
            "saves": 0,
            "bonus": 0,
            "bps": 2,
            "influence": "3.8",
            "creativity": "1.0",
            "threat": "1.0",
            "ict_index": "0.6",
            "starts": 0,
            "expected_goals": "0.03",
            "expected_assists": "0.02",
            "expected_goal_involvements": "0.05",
            "expected_goals_conceded": "0.32",
            "value": 72,
            "transfers_balance": -7931,
            "selected": 228130,
            "transfers_in": 5664,
            "transfers_out": 13595
        },
        {
            "element": 297,
            "fixture": 105,
            "opponent_team": 12,
            "total_points": 1,
            "was_home": false,
            "kickoff_time": "2023-11-05T16:30:00Z",
            "team_h_score": 1,
            "team_a_score": 1,
            "round": 11,
            "minutes": 24,
            "goals_scored": 0,
            "assists": 0,
            "clean_sheets": 0,
            "goals_conceded": 1,
            "own_goals": 0,
            "penalties_saved": 0,
            "penalties_missed": 0,
            "yellow_cards": 0,
            "red_cards": 0,
            "saves": 0,
            "bonus": 0,
            "bps": -1,
            "influence": "0.0",
            "creativity": "0.6",
            "threat": "12.0",
            "ict_index": "1.1",
            "starts": 0,
            "expected_goals": "0.60",
            "expected_assists": "0.03",
            "expected_goal_involvements": "0.63",
            "expected_goals_conceded": "0.45",
            "value": 72,
            "transfers_balance": -16,
            "selected": 229481,
            "transfers_in": 8901,
            "transfers_out": 8917
        },
        {
            "element": 297,
            "fixture": 117,
            "opponent_team": 4,
            "total_points": 2,
            "was_home": true,
            "kickoff_time": "2023-11-12T14:00:00Z",
            "team_h_score": 3,
            "team_a_score": 0,
            "round": 12,
            "minutes": 82,
            "goals_scored": 0,
            "assists": 0,
            "clean_sheets": 1,
            "goals_conceded": 0,
            "own_goals": 0,
            "penalties_saved": 0,
            "penalties_missed": 0,
            "yellow_cards": 0,
            "red_cards": 0,
            "saves": 0,
            "bonus": 0,
            "bps": 13,
            "influence": "6.4",
            "creativity": "5.0",
            "threat": "14.0",
            "ict_index": "2.5",
            "starts": 1,
            "expected_goals": "0.05",
            "expected_assists": "0.04",
            "expected_goal_involvements": "0.09",
            "expected_goals_conceded": "1.50",
            "value": 72,
            "transfers_balance": -417,
            "selected": 230637,
            "transfers_in": 7438,
            "transfers_out": 7855
        }
    ],
    "history_past": [
        {
            "season_name": "2022/23",
            "element_code": 243298,
            "start_cost": 80,
            "end_cost": 76,
            "total_points": 90,
            "minutes": 1455,
            "goals_scored": 7,
            "assists": 3,
            "clean_sheets": 6,
            "goals_conceded": 19,
            "own_goals": 0,
            "penalties_saved": 0,
            "penalties_missed": 0,
            "yellow_cards": 0,
            "red_cards": 0,
            "saves": 0,
            "bonus": 4,
            "bps": 256,
            "influence": "375.6",
            "creativity": "292.4",
            "threat": "460.0",
            "ict_index": "112.3",
            "starts": 17,
            "expected_goals": "6.43",
            "expected_assists": "1.87",
            "expected_goal_involvements": "8.30",
            "expected_goals_conceded": "19.56"
        }
    ]
}